{
  "klass": "Specie",
  "id": 347,
  "dbSymbol": "anorith",
  "forms": [
    {
      "form": 0,
      "height": 0.7,
      "weight": 12.5,
      "type1": "rock",
      "type2": "bug",
      "baseHp": 45,
      "baseAtk": 95,
      "baseDfe": 50,
      "baseSpd": 75,
      "baseAts": 40,
      "baseDfs": 50,
      "evHp": 0,
      "evAtk": 1,
      "evDfe": 0,
      "evSpd": 0,
      "evAts": 0,
      "evDfs": 0,
      "evolutions": [
        {
          "dbSymbol": "armaldo",
          "form": 0,
          "conditions": [
            {
              "type": "minLevel",
              "value": 40
            }
          ]
        }
      ],
      "experienceType": 4,
      "baseExperience": 71,
      "baseLoyalty": 70,
      "catchRate": 45,
      "femaleRate": 12.5,
      "breedGroups": [
        9,
        9
      ],
      "hatchSteps": 7680,
      "babyDbSymbol": "anorith",
      "babyForm": 0,
      "itemHeld": [
        {
          "dbSymbol": "none",
          "chance": 0
        },
        {
          "dbSymbol": "none",
          "chance": 0
        }
      ],
      "abilities": [
        "battle_armor",
        "battle_armor",
        "swift_swim"
      ],
      "frontOffsetY": 0,
      "moveSet": [
        {
          "klass": "LevelLearnableMove",
          "move": "harden",
          "level": 1
        },
        {
          "klass": "LevelLearnableMove",
          "move": "scratch",
          "level": 1
        },
        {
          "klass": "LevelLearnableMove",
          "move": "mud_sport",
          "level": 4
        },
        {
          "klass": "LevelLearnableMove",
          "move": "water_gun",
          "level": 7
        },
        {
          "klass": "LevelLearnableMove",
          "move": "fury_cutter",
          "level": 10
        },
        {
          "klass": "LevelLearnableMove",
          "move": "smack_down",
          "level": 13
        },
        {
          "klass": "LevelLearnableMove",
          "move": "metal_claw",
          "level": 17
        },
        {
          "klass": "LevelLearnableMove",
          "move": "ancient_power",
          "level": 21
        },
        {
          "klass": "LevelLearnableMove",
          "move": "bug_bite",
          "level": 25
        },
        {
          "klass": "LevelLearnableMove",
          "move": "brine",
          "level": 29
        },
        {
          "klass": "LevelLearnableMove",
          "move": "slash",
          "level": 34
        },
        {
          "klass": "LevelLearnableMove",
          "move": "crush_claw",
          "level": 39
        },
        {
          "klass": "LevelLearnableMove",
          "move": "x_scissor",
          "level": 44
        },
        {
          "klass": "LevelLearnableMove",
          "move": "protect",
          "level": 49
        },
        {
          "klass": "LevelLearnableMove",
          "move": "rock_blast",
          "level": 55
        },
        {
          "klass": "TutorLearnableMove",
          "move": "iron_defense"
        },
        {
          "klass": "TutorLearnableMove",
          "move": "stealth_rock"
        },
        {
          "klass": "TutorLearnableMove",
          "move": "bug_bite"
        },
        {
          "klass": "TutorLearnableMove",
          "move": "snore"
        },
        {
          "klass": "TutorLearnableMove",
          "move": "knock_off"
        },
        {
          "klass": "TutorLearnableMove",
          "move": "earth_power"
        },
        {
          "klass": "TutorLearnableMove",
          "move": "water_pulse"
        },
        {
          "klass": "TechLearnableMove",
          "move": "toxic"
        },
        {
          "klass": "TechLearnableMove",
          "move": "hidden_power"
        },
        {
          "klass": "TechLearnableMove",
          "move": "sunny_day"
        },
        {
          "klass": "TechLearnableMove",
          "move": "protect"
        },
        {
          "klass": "TechLearnableMove",
          "move": "frustration"
        },
        {
          "klass": "TechLearnableMove",
          "move": "smack_down"
        },
        {
          "klass": "TechLearnableMove",
          "move": "return"
        },
        {
          "klass": "TechLearnableMove",
          "move": "brick_break"
        },
        {
          "klass": "TechLearnableMove",
          "move": "double_team"
        },
        {
          "klass": "TechLearnableMove",
          "move": "sandstorm"
        },
        {
          "klass": "TechLearnableMove",
          "move": "rock_tomb"
        },
        {
          "klass": "TechLearnableMove",
          "move": "aerial_ace"
        },
        {
          "klass": "TechLearnableMove",
          "move": "facade"
        },
        {
          "klass": "TechLearnableMove",
          "move": "rest"
        },
        {
          "klass": "TechLearnableMove",
          "move": "attract"
        },
        {
          "klass": "TechLearnableMove",
          "move": "round"
        },
        {
          "klass": "TechLearnableMove",
          "move": "false_swipe"
        },
        {
          "klass": "TechLearnableMove",
          "move": "rock_polish"
        },
        {
          "klass": "TechLearnableMove",
          "move": "swords_dance"
        },
        {
          "klass": "TechLearnableMove",
          "move": "rock_slide"
        },
        {
          "klass": "TechLearnableMove",
          "move": "x_scissor"
        },
        {
          "klass": "TechLearnableMove",
          "move": "swagger"
        },
        {
          "klass": "TechLearnableMove",
          "move": "sleep_talk"
        },
        {
          "klass": "TechLearnableMove",
          "move": "substitute"
        },
        {
          "klass": "TechLearnableMove",
          "move": "confide"
        },
        {
          "klass": "TechLearnableMove",
          "move": "struggle_bug"
        },
        {
          "klass": "TechLearnableMove",
          "move": "secret_power"
        },
        {
          "klass": "TechLearnableMove",
          "move": "cut"
        },
        {
          "klass": "TechLearnableMove",
          "move": "rock_smash"
        },
        {
          "klass": "BreedLearnableMove",
          "move": "aqua_jet"
        },
        {
          "klass": "BreedLearnableMove",
          "move": "cross_poison"
        },
        {
          "klass": "BreedLearnableMove",
          "move": "curse"
        },
        {
          "klass": "BreedLearnableMove",
          "move": "iron_defense"
        },
        {
          "klass": "BreedLearnableMove",
          "move": "knock_off"
        },
        {
          "klass": "BreedLearnableMove",
          "move": "rapid_spin"
        },
        {
          "klass": "BreedLearnableMove",
          "move": "sand_attack"
        },
        {
          "klass": "BreedLearnableMove",
          "move": "screech"
        },
        {
          "klass": "BreedLearnableMove",
          "move": "water_pulse"
        }
      ],
      "resources": {
        "icon": "347",
        "iconShiny": "",
        "front": "347",
        "frontShiny": "347",
        "back": "347",
        "backShiny": "347",
        "footprint": "347",
        "character": "347_0",
        "characterShiny": "347s_0",
        "cry": "347cry.ogg",
        "hasFemale": false
      }
    }
  ]
}