{
  "klass": "Specie",
  "id": 24,
  "dbSymbol": "arbok",
  "forms": [
    {
      "form": 0,
      "height": 3.5,
      "weight": 65,
      "type1": "poison",
      "type2": "__undef__",
      "baseHp": 60,
      "baseAtk": 95,
      "baseDfe": 69,
      "baseSpd": 80,
      "baseAts": 65,
      "baseDfs": 79,
      "evHp": 0,
      "evAtk": 2,
      "evDfe": 0,
      "evSpd": 0,
      "evAts": 0,
      "evDfs": 0,
      "evolutions": [],
      "experienceType": 1,
      "baseExperience": 157,
      "baseLoyalty": 70,
      "catchRate": 90,
      "femaleRate": 50,
      "breedGroups": [
        5,
        14
      ],
      "hatchSteps": 5120,
      "babyDbSymbol": "ekans",
      "babyForm": 0,
      "itemHeld": [
        {
          "dbSymbol": "none",
          "chance": 0
        },
        {
          "dbSymbol": "none",
          "chance": 0
        }
      ],
      "abilities": [
        "intimidate",
        "shed_skin",
        "unnerve"
      ],
      "frontOffsetY": 0,
      "moveSet": [
        {
          "klass": "LevelLearnableMove",
          "move": "ice_fang",
          "level": 1
        },
        {
          "klass": "LevelLearnableMove",
          "move": "thunder_fang",
          "level": 1
        },
        {
          "klass": "LevelLearnableMove",
          "move": "fire_fang",
          "level": 1
        },
        {
          "klass": "LevelLearnableMove",
          "move": "leer",
          "level": 1
        },
        {
          "klass": "LevelLearnableMove",
          "move": "wrap",
          "level": 1
        },
        {
          "klass": "LevelLearnableMove",
          "move": "bite",
          "level": 1
        },
        {
          "klass": "LevelLearnableMove",
          "move": "poison_sting",
          "level": 1
        },
        {
          "klass": "LevelLearnableMove",
          "move": "crunch",
          "level": 1
        },
        {
          "klass": "LevelLearnableMove",
          "move": "poison_sting",
          "level": 4
        },
        {
          "klass": "LevelLearnableMove",
          "move": "bite",
          "level": 9
        },
        {
          "klass": "LevelLearnableMove",
          "move": "glare",
          "level": 12
        },
        {
          "klass": "LevelLearnableMove",
          "move": "screech",
          "level": 17
        },
        {
          "klass": "LevelLearnableMove",
          "move": "acid",
          "level": 20
        },
        {
          "klass": "LevelLearnableMove",
          "move": "stockpile",
          "level": 27
        },
        {
          "klass": "LevelLearnableMove",
          "move": "swallow",
          "level": 27
        },
        {
          "klass": "LevelLearnableMove",
          "move": "spit_up",
          "level": 27
        },
        {
          "klass": "LevelLearnableMove",
          "move": "acid_spray",
          "level": 32
        },
        {
          "klass": "LevelLearnableMove",
          "move": "mud_bomb",
          "level": 39
        },
        {
          "klass": "LevelLearnableMove",
          "move": "gastro_acid",
          "level": 44
        },
        {
          "klass": "LevelLearnableMove",
          "move": "belch",
          "level": 48
        },
        {
          "klass": "LevelLearnableMove",
          "move": "haze",
          "level": 51
        },
        {
          "klass": "LevelLearnableMove",
          "move": "coil",
          "level": 56
        },
        {
          "klass": "LevelLearnableMove",
          "move": "gunk_shot",
          "level": 63
        },
        {
          "klass": "TutorLearnableMove",
          "move": "seed_bomb"
        },
        {
          "klass": "TutorLearnableMove",
          "move": "spite"
        },
        {
          "klass": "TutorLearnableMove",
          "move": "gunk_shot"
        },
        {
          "klass": "TutorLearnableMove",
          "move": "bind"
        },
        {
          "klass": "TutorLearnableMove",
          "move": "giga_drain"
        },
        {
          "klass": "TutorLearnableMove",
          "move": "aqua_tail"
        },
        {
          "klass": "TutorLearnableMove",
          "move": "iron_tail"
        },
        {
          "klass": "TutorLearnableMove",
          "move": "snore"
        },
        {
          "klass": "TutorLearnableMove",
          "move": "snatch"
        },
        {
          "klass": "TutorLearnableMove",
          "move": "gastro_acid"
        },
        {
          "klass": "TutorLearnableMove",
          "move": "throat_chop"
        },
        {
          "klass": "TutorLearnableMove",
          "move": "stomping_tantrum"
        },
        {
          "klass": "TechLearnableMove",
          "move": "toxic"
        },
        {
          "klass": "TechLearnableMove",
          "move": "venoshock"
        },
        {
          "klass": "TechLearnableMove",
          "move": "hidden_power"
        },
        {
          "klass": "TechLearnableMove",
          "move": "sunny_day"
        },
        {
          "klass": "TechLearnableMove",
          "move": "hyper_beam"
        },
        {
          "klass": "TechLearnableMove",
          "move": "protect"
        },
        {
          "klass": "TechLearnableMove",
          "move": "rain_dance"
        },
        {
          "klass": "TechLearnableMove",
          "move": "frustration"
        },
        {
          "klass": "TechLearnableMove",
          "move": "earthquake"
        },
        {
          "klass": "TechLearnableMove",
          "move": "return"
        },
        {
          "klass": "TechLearnableMove",
          "move": "double_team"
        },
        {
          "klass": "TechLearnableMove",
          "move": "sludge_wave"
        },
        {
          "klass": "TechLearnableMove",
          "move": "sludge_bomb"
        },
        {
          "klass": "TechLearnableMove",
          "move": "rock_tomb"
        },
        {
          "klass": "TechLearnableMove",
          "move": "torment"
        },
        {
          "klass": "TechLearnableMove",
          "move": "facade"
        },
        {
          "klass": "TechLearnableMove",
          "move": "rest"
        },
        {
          "klass": "TechLearnableMove",
          "move": "attract"
        },
        {
          "klass": "TechLearnableMove",
          "move": "thief"
        },
        {
          "klass": "TechLearnableMove",
          "move": "round"
        },
        {
          "klass": "TechLearnableMove",
          "move": "brutal_swing"
        },
        {
          "klass": "TechLearnableMove",
          "move": "payback"
        },
        {
          "klass": "TechLearnableMove",
          "move": "giga_impact"
        },
        {
          "klass": "TechLearnableMove",
          "move": "bulldoze"
        },
        {
          "klass": "TechLearnableMove",
          "move": "rock_slide"
        },
        {
          "klass": "TechLearnableMove",
          "move": "dragon_tail"
        },
        {
          "klass": "TechLearnableMove",
          "move": "infestation"
        },
        {
          "klass": "TechLearnableMove",
          "move": "poison_jab"
        },
        {
          "klass": "TechLearnableMove",
          "move": "swagger"
        },
        {
          "klass": "TechLearnableMove",
          "move": "sleep_talk"
        },
        {
          "klass": "TechLearnableMove",
          "move": "substitute"
        },
        {
          "klass": "TechLearnableMove",
          "move": "dark_pulse"
        },
        {
          "klass": "TechLearnableMove",
          "move": "confide"
        },
        {
          "klass": "TechLearnableMove",
          "move": "secret_power"
        },
        {
          "klass": "TechLearnableMove",
          "move": "strength"
        },
        {
          "klass": "EvolutionLearnableMove",
          "move": "crunch"
        }
      ],
      "resources": {
        "icon": "024",
        "iconShiny": "",
        "front": "024",
        "frontShiny": "024",
        "back": "024",
        "backShiny": "024",
        "footprint": "024",
        "character": "024_0",
        "characterShiny": "024s_0",
        "cry": "024cry.ogg",
        "hasFemale": false
      }
    }
  ]
}