{
  "klass": "Specie",
  "id": 438,
  "dbSymbol": "bonsly",
  "forms": [
    {
      "form": 0,
      "height": 0.5,
      "weight": 15,
      "type1": "rock",
      "type2": "__undef__",
      "baseHp": 50,
      "baseAtk": 80,
      "baseDfe": 95,
      "baseSpd": 10,
      "baseAts": 10,
      "baseDfs": 45,
      "evHp": 0,
      "evAtk": 0,
      "evDfe": 1,
      "evSpd": 0,
      "evAts": 0,
      "evDfs": 0,
      "evolutions": [
        {
          "dbSymbol": "sudowoodo",
          "form": 0,
          "conditions": [
            {
              "type": "skill1",
              "value": "mimic"
            }
          ]
        }
      ],
      "experienceType": 1,
      "baseExperience": 58,
      "baseLoyalty": 70,
      "catchRate": 255,
      "femaleRate": 50,
      "breedGroups": [
        15,
        15
      ],
      "hatchSteps": 5120,
      "babyDbSymbol": "__undef__",
      "babyForm": 0,
      "itemHeld": [
        {
          "dbSymbol": "none",
          "chance": 0
        },
        {
          "dbSymbol": "none",
          "chance": 0
        }
      ],
      "abilities": [
        "sturdy",
        "rock_head",
        "rattled"
      ],
      "frontOffsetY": 0,
      "moveSet": [
        {
          "klass": "LevelLearnableMove",
          "move": "fake_tears",
          "level": 1
        },
        {
          "klass": "LevelLearnableMove",
          "move": "copycat",
          "level": 1
        },
        {
          "klass": "LevelLearnableMove",
          "move": "flail",
          "level": 5
        },
        {
          "klass": "LevelLearnableMove",
          "move": "low_kick",
          "level": 8
        },
        {
          "klass": "LevelLearnableMove",
          "move": "rock_throw",
          "level": 12
        },
        {
          "klass": "LevelLearnableMove",
          "move": "mimic",
          "level": 15
        },
        {
          "klass": "LevelLearnableMove",
          "move": "feint_attack",
          "level": 19
        },
        {
          "klass": "LevelLearnableMove",
          "move": "tearful_look",
          "level": 22
        },
        {
          "klass": "LevelLearnableMove",
          "move": "rock_tomb",
          "level": 26
        },
        {
          "klass": "LevelLearnableMove",
          "move": "block",
          "level": 29
        },
        {
          "klass": "LevelLearnableMove",
          "move": "rock_slide",
          "level": 33
        },
        {
          "klass": "LevelLearnableMove",
          "move": "counter",
          "level": 36
        },
        {
          "klass": "LevelLearnableMove",
          "move": "sucker_punch",
          "level": 40
        },
        {
          "klass": "LevelLearnableMove",
          "move": "double_edge",
          "level": 43
        },
        {
          "klass": "TutorLearnableMove",
          "move": "after_you"
        },
        {
          "klass": "TutorLearnableMove",
          "move": "low_kick"
        },
        {
          "klass": "TutorLearnableMove",
          "move": "block"
        },
        {
          "klass": "TutorLearnableMove",
          "move": "uproar"
        },
        {
          "klass": "TutorLearnableMove",
          "move": "helping_hand"
        },
        {
          "klass": "TutorLearnableMove",
          "move": "role_play"
        },
        {
          "klass": "TutorLearnableMove",
          "move": "covet"
        },
        {
          "klass": "TutorLearnableMove",
          "move": "stealth_rock"
        },
        {
          "klass": "TutorLearnableMove",
          "move": "snore"
        },
        {
          "klass": "TutorLearnableMove",
          "move": "earth_power"
        },
        {
          "klass": "TutorLearnableMove",
          "move": "stomping_tantrum"
        },
        {
          "klass": "TutorLearnableMove",
          "move": "foul_play"
        },
        {
          "klass": "TechLearnableMove",
          "move": "calm_mind"
        },
        {
          "klass": "TechLearnableMove",
          "move": "toxic"
        },
        {
          "klass": "TechLearnableMove",
          "move": "hidden_power"
        },
        {
          "klass": "TechLearnableMove",
          "move": "sunny_day"
        },
        {
          "klass": "TechLearnableMove",
          "move": "protect"
        },
        {
          "klass": "TechLearnableMove",
          "move": "frustration"
        },
        {
          "klass": "TechLearnableMove",
          "move": "smack_down"
        },
        {
          "klass": "TechLearnableMove",
          "move": "return"
        },
        {
          "klass": "TechLearnableMove",
          "move": "brick_break"
        },
        {
          "klass": "TechLearnableMove",
          "move": "double_team"
        },
        {
          "klass": "TechLearnableMove",
          "move": "sandstorm"
        },
        {
          "klass": "TechLearnableMove",
          "move": "rock_tomb"
        },
        {
          "klass": "TechLearnableMove",
          "move": "facade"
        },
        {
          "klass": "TechLearnableMove",
          "move": "rest"
        },
        {
          "klass": "TechLearnableMove",
          "move": "attract"
        },
        {
          "klass": "TechLearnableMove",
          "move": "thief"
        },
        {
          "klass": "TechLearnableMove",
          "move": "round"
        },
        {
          "klass": "TechLearnableMove",
          "move": "explosion"
        },
        {
          "klass": "TechLearnableMove",
          "move": "rock_polish"
        },
        {
          "klass": "TechLearnableMove",
          "move": "psych_up"
        },
        {
          "klass": "TechLearnableMove",
          "move": "rock_slide"
        },
        {
          "klass": "TechLearnableMove",
          "move": "swagger"
        },
        {
          "klass": "TechLearnableMove",
          "move": "sleep_talk"
        },
        {
          "klass": "TechLearnableMove",
          "move": "substitute"
        },
        {
          "klass": "TechLearnableMove",
          "move": "nature_power"
        },
        {
          "klass": "TechLearnableMove",
          "move": "confide"
        },
        {
          "klass": "TechLearnableMove",
          "move": "secret_power"
        },
        {
          "klass": "BreedLearnableMove",
          "move": "curse"
        },
        {
          "klass": "BreedLearnableMove",
          "move": "defense_curl"
        },
        {
          "klass": "BreedLearnableMove",
          "move": "endure"
        },
        {
          "klass": "BreedLearnableMove",
          "move": "harden"
        },
        {
          "klass": "BreedLearnableMove",
          "move": "headbutt"
        },
        {
          "klass": "BreedLearnableMove",
          "move": "rollout"
        },
        {
          "klass": "BreedLearnableMove",
          "move": "sand_tomb"
        },
        {
          "klass": "BreedLearnableMove",
          "move": "self_destruct"
        },
        {
          "klass": "BreedLearnableMove",
          "move": "stealth_rock"
        }
      ],
      "resources": {
        "icon": "438",
        "iconShiny": "",
        "front": "438",
        "frontShiny": "438",
        "back": "438",
        "backShiny": "438",
        "footprint": "438",
        "character": "438_0",
        "characterShiny": "438s_0",
        "cry": "438cry.ogg",
        "hasFemale": false
      }
    }
  ]
}