{
  "klass": "Specie",
  "id": 205,
  "dbSymbol": "forretress",
  "forms": [
    {
      "form": 0,
      "height": 1.2,
      "weight": 125.8,
      "type1": "bug",
      "type2": "steel",
      "baseHp": 75,
      "baseAtk": 90,
      "baseDfe": 140,
      "baseSpd": 40,
      "baseAts": 60,
      "baseDfs": 60,
      "evHp": 0,
      "evAtk": 0,
      "evDfe": 2,
      "evSpd": 0,
      "evAts": 0,
      "evDfs": 0,
      "evolutions": [],
      "experienceType": 1,
      "baseExperience": 163,
      "baseLoyalty": 70,
      "catchRate": 75,
      "femaleRate": 50,
      "breedGroups": [
        3,
        3
      ],
      "hatchSteps": 5120,
      "babyDbSymbol": "pineco",
      "babyForm": 0,
      "itemHeld": [
        {
          "dbSymbol": "none",
          "chance": 0
        },
        {
          "dbSymbol": "none",
          "chance": 0
        }
      ],
      "abilities": [
        "sturdy",
        "sturdy",
        "overcoat"
      ],
      "frontOffsetY": 0,
      "resources": {
        "icon": "0205",
        "iconShiny": "0205s",
        "front": "0205",
        "frontShiny": "0205s",
        "back": "0205",
        "backShiny": "0205s",
        "footprint": "0205",
        "character": "0205",
        "characterShiny": "0205s",
        "cry": "0205.ogg",
        "hasFemale": false,
        "egg": "egg",
        "iconEgg": "egg"
      },
      "moveSet": [
        {
          "move": "tackle",
          "klass": "LevelLearnableMove",
          "level": 1
        },
        {
          "move": "self_destruct",
          "klass": "LevelLearnableMove",
          "level": 1
        },
        {
          "move": "protect",
          "klass": "LevelLearnableMove",
          "level": 1
        },
        {
          "move": "zap_cannon",
          "klass": "LevelLearnableMove",
          "level": 1
        },
        {
          "move": "toxic_spikes",
          "klass": "LevelLearnableMove",
          "level": 1
        },
        {
          "move": "magnet_rise",
          "klass": "LevelLearnableMove",
          "level": 1
        },
        {
          "move": "mirror_shot",
          "klass": "LevelLearnableMove",
          "level": 1
        },
        {
          "move": "bug_bite",
          "klass": "LevelLearnableMove",
          "level": 1
        },
        {
          "move": "autotomize",
          "klass": "LevelLearnableMove",
          "level": 1
        },
        {
          "move": "heavy_slam",
          "klass": "LevelLearnableMove",
          "level": 1
        },
        {
          "move": "self_destruct",
          "klass": "LevelLearnableMove",
          "level": 6
        },
        {
          "move": "bug_bite",
          "klass": "LevelLearnableMove",
          "level": 9
        },
        {
          "move": "take_down",
          "klass": "LevelLearnableMove",
          "level": 12
        },
        {
          "move": "rapid_spin",
          "klass": "LevelLearnableMove",
          "level": 17
        },
        {
          "move": "bide",
          "klass": "LevelLearnableMove",
          "level": 20
        },
        {
          "move": "natural_gift",
          "klass": "LevelLearnableMove",
          "level": 23
        },
        {
          "move": "spikes",
          "klass": "LevelLearnableMove",
          "level": 28
        },
        {
          "move": "payback",
          "klass": "LevelLearnableMove",
          "level": 32
        },
        {
          "move": "explosion",
          "klass": "LevelLearnableMove",
          "level": 36
        },
        {
          "move": "iron_defense",
          "klass": "LevelLearnableMove",
          "level": 42
        },
        {
          "move": "gyro_ball",
          "klass": "LevelLearnableMove",
          "level": 46
        },
        {
          "move": "double_edge",
          "klass": "LevelLearnableMove",
          "level": 50
        },
        {
          "move": "magnet_rise",
          "klass": "LevelLearnableMove",
          "level": 56
        },
        {
          "move": "zap_cannon",
          "klass": "LevelLearnableMove",
          "level": 60
        },
        {
          "move": "heavy_slam",
          "klass": "LevelLearnableMove",
          "level": 64
        },
        {
          "move": "hyper_beam",
          "klass": "TechLearnableMove"
        },
        {
          "move": "solar_beam",
          "klass": "TechLearnableMove"
        },
        {
          "move": "earthquake",
          "klass": "TechLearnableMove"
        },
        {
          "move": "toxic",
          "klass": "TechLearnableMove"
        },
        {
          "move": "double_team",
          "klass": "TechLearnableMove"
        },
        {
          "move": "light_screen",
          "klass": "TechLearnableMove"
        },
        {
          "move": "reflect",
          "klass": "TechLearnableMove"
        },
        {
          "move": "explosion",
          "klass": "TechLearnableMove"
        },
        {
          "move": "rest",
          "klass": "TechLearnableMove"
        },
        {
          "move": "rock_slide",
          "klass": "TechLearnableMove"
        },
        {
          "move": "substitute",
          "klass": "TechLearnableMove"
        },
        {
          "move": "snore",
          "klass": "TutorLearnableMove"
        },
        {
          "move": "protect",
          "klass": "TechLearnableMove"
        },
        {
          "move": "sandstorm",
          "klass": "TechLearnableMove"
        },
        {
          "move": "giga_drain",
          "klass": "TutorLearnableMove"
        },
        {
          "move": "swagger",
          "klass": "TechLearnableMove"
        },
        {
          "move": "attract",
          "klass": "TechLearnableMove"
        },
        {
          "move": "sleep_talk",
          "klass": "TechLearnableMove"
        },
        {
          "move": "return",
          "klass": "TechLearnableMove"
        },
        {
          "move": "frustration",
          "klass": "TechLearnableMove"
        },
        {
          "move": "pain_split",
          "klass": "TutorLearnableMove"
        },
        {
          "move": "hidden_power",
          "klass": "TechLearnableMove"
        },
        {
          "move": "sunny_day",
          "klass": "TechLearnableMove"
        },
        {
          "move": "facade",
          "klass": "TechLearnableMove"
        },
        {
          "move": "rock_tomb",
          "klass": "TechLearnableMove"
        },
        {
          "move": "signal_beam",
          "klass": "TutorLearnableMove"
        },
        {
          "move": "iron_defense",
          "klass": "TutorLearnableMove"
        },
        {
          "move": "block",
          "klass": "TutorLearnableMove"
        },
        {
          "move": "gravity",
          "klass": "TutorLearnableMove"
        },
        {
          "move": "gyro_ball",
          "klass": "TechLearnableMove"
        },
        {
          "move": "payback",
          "klass": "TechLearnableMove"
        },
        {
          "move": "magnet_rise",
          "klass": "TutorLearnableMove"
        },
        {
          "move": "rock_polish",
          "klass": "TechLearnableMove"
        },
        {
          "move": "giga_impact",
          "klass": "TechLearnableMove"
        },
        {
          "move": "mirror_shot",
          "klass": "EvolutionLearnableMove"
        },
        {
          "move": "flash_cannon",
          "klass": "TechLearnableMove"
        },
        {
          "move": "stealth_rock",
          "klass": "TutorLearnableMove"
        },
        {
          "move": "bug_bite",
          "klass": "TutorLearnableMove"
        },
        {
          "move": "venoshock",
          "klass": "TechLearnableMove"
        },
        {
          "move": "autotomize",
          "klass": "EvolutionLearnableMove"
        },
        {
          "move": "telekinesis",
          "klass": "TutorLearnableMove"
        },
        {
          "move": "round",
          "klass": "TechLearnableMove"
        },
        {
          "move": "ally_switch",
          "klass": "TutorLearnableMove"
        },
        {
          "move": "volt_switch",
          "klass": "TechLearnableMove"
        },
        {
          "move": "bulldoze",
          "klass": "TechLearnableMove"
        },
        {
          "move": "drill_run",
          "klass": "TutorLearnableMove"
        },
        {
          "move": "confide",
          "klass": "TechLearnableMove"
        },
        {
          "move": "laser_focus",
          "klass": "TutorLearnableMove"
        },
        {
          "move": "rock_smash",
          "klass": "TechLearnableMove"
        },
        {
          "move": "strength",
          "klass": "TechLearnableMove"
        }
      ],
      "formTextId": {
        "name": 272,
        "description": 0
      }
    }
  ]
}