{
  "klass": "Specie",
  "id": 231,
  "dbSymbol": "phanpy",
  "forms": [
    {
      "form": 0,
      "height": 0.5,
      "weight": 33.5,
      "type1": "ground",
      "type2": "__undef__",
      "baseHp": 90,
      "baseAtk": 60,
      "baseDfe": 60,
      "baseSpd": 40,
      "baseAts": 40,
      "baseDfs": 40,
      "evHp": 1,
      "evAtk": 0,
      "evDfe": 0,
      "evSpd": 0,
      "evAts": 0,
      "evDfs": 0,
      "evolutions": [
        {
          "dbSymbol": "donphan",
          "form": 0,
          "conditions": [
            {
              "type": "minLevel",
              "value": 25
            }
          ]
        }
      ],
      "experienceType": 1,
      "baseExperience": 66,
      "baseLoyalty": 70,
      "catchRate": 120,
      "femaleRate": 50,
      "breedGroups": [
        5,
        5
      ],
      "hatchSteps": 5120,
      "babyDbSymbol": "phanpy",
      "babyForm": 0,
      "itemHeld": [
        {
          "dbSymbol": "none",
          "chance": 0
        },
        {
          "dbSymbol": "none",
          "chance": 0
        }
      ],
      "abilities": [
        "pickup",
        "pickup",
        "sand_veil"
      ],
      "frontOffsetY": 0,
      "resources": {
        "icon": "0231",
        "iconShiny": "0231s",
        "front": "0231",
        "frontShiny": "0231s",
        "back": "0231",
        "backShiny": "0231s",
        "footprint": "0231",
        "character": "0231",
        "characterShiny": "0231s",
        "cry": "0231.ogg",
        "hasFemale": false,
        "egg": "egg",
        "iconEgg": "egg"
      },
      "moveSet": [
        {
          "move": "tackle",
          "klass": "LevelLearnableMove",
          "level": 1
        },
        {
          "move": "growl",
          "klass": "LevelLearnableMove",
          "level": 1
        },
        {
          "move": "defense_curl",
          "klass": "LevelLearnableMove",
          "level": 1
        },
        {
          "move": "odor_sleuth",
          "klass": "LevelLearnableMove",
          "level": 1
        },
        {
          "move": "flail",
          "klass": "LevelLearnableMove",
          "level": 6
        },
        {
          "move": "rollout",
          "klass": "LevelLearnableMove",
          "level": 10
        },
        {
          "move": "natural_gift",
          "klass": "LevelLearnableMove",
          "level": 15
        },
        {
          "move": "endure",
          "klass": "LevelLearnableMove",
          "level": 19
        },
        {
          "move": "slam",
          "klass": "LevelLearnableMove",
          "level": 24
        },
        {
          "move": "take_down",
          "klass": "LevelLearnableMove",
          "level": 28
        },
        {
          "move": "charm",
          "klass": "LevelLearnableMove",
          "level": 33
        },
        {
          "move": "last_resort",
          "klass": "LevelLearnableMove",
          "level": 37
        },
        {
          "move": "double_edge",
          "klass": "LevelLearnableMove",
          "level": 42
        },
        {
          "move": "body_slam",
          "klass": "BreedLearnableMove"
        },
        {
          "move": "roar",
          "klass": "TechLearnableMove"
        },
        {
          "move": "counter",
          "klass": "BreedLearnableMove"
        },
        {
          "move": "earthquake",
          "klass": "TechLearnableMove"
        },
        {
          "move": "fissure",
          "klass": "BreedLearnableMove"
        },
        {
          "move": "toxic",
          "klass": "TechLearnableMove"
        },
        {
          "move": "double_team",
          "klass": "TechLearnableMove"
        },
        {
          "move": "focus_energy",
          "klass": "BreedLearnableMove"
        },
        {
          "move": "rest",
          "klass": "TechLearnableMove"
        },
        {
          "move": "rock_slide",
          "klass": "TechLearnableMove"
        },
        {
          "move": "substitute",
          "klass": "TechLearnableMove"
        },
        {
          "move": "snore",
          "klass": "BreedLearnableMove"
        },
        {
          "move": "snore",
          "klass": "TutorLearnableMove"
        },
        {
          "move": "protect",
          "klass": "TechLearnableMove"
        },
        {
          "move": "mud_slap",
          "klass": "BreedLearnableMove"
        },
        {
          "move": "sandstorm",
          "klass": "TechLearnableMove"
        },
        {
          "move": "swagger",
          "klass": "TechLearnableMove"
        },
        {
          "move": "attract",
          "klass": "TechLearnableMove"
        },
        {
          "move": "sleep_talk",
          "klass": "TechLearnableMove"
        },
        {
          "move": "return",
          "klass": "TechLearnableMove"
        },
        {
          "move": "frustration",
          "klass": "TechLearnableMove"
        },
        {
          "move": "iron_tail",
          "klass": "TutorLearnableMove"
        },
        {
          "move": "hidden_power",
          "klass": "TechLearnableMove"
        },
        {
          "move": "sunny_day",
          "klass": "TechLearnableMove"
        },
        {
          "move": "ancient_power",
          "klass": "BreedLearnableMove"
        },
        {
          "move": "facade",
          "klass": "TechLearnableMove"
        },
        {
          "move": "superpower",
          "klass": "TutorLearnableMove"
        },
        {
          "move": "knock_off",
          "klass": "TutorLearnableMove"
        },
        {
          "move": "endeavor",
          "klass": "BreedLearnableMove"
        },
        {
          "move": "endeavor",
          "klass": "TutorLearnableMove"
        },
        {
          "move": "hyper_voice",
          "klass": "TutorLearnableMove"
        },
        {
          "move": "rock_tomb",
          "klass": "TechLearnableMove"
        },
        {
          "move": "last_resort",
          "klass": "TutorLearnableMove"
        },
        {
          "move": "seed_bomb",
          "klass": "TutorLearnableMove"
        },
        {
          "move": "earth_power",
          "klass": "TutorLearnableMove"
        },
        {
          "move": "ice_shard",
          "klass": "BreedLearnableMove"
        },
        {
          "move": "gunk_shot",
          "klass": "TutorLearnableMove"
        },
        {
          "move": "stealth_rock",
          "klass": "TutorLearnableMove"
        },
        {
          "move": "head_smash",
          "klass": "BreedLearnableMove"
        },
        {
          "move": "heavy_slam",
          "klass": "BreedLearnableMove"
        },
        {
          "move": "round",
          "klass": "TechLearnableMove"
        },
        {
          "move": "echoed_voice",
          "klass": "TechLearnableMove"
        },
        {
          "move": "bulldoze",
          "klass": "TechLearnableMove"
        },
        {
          "move": "play_rough",
          "klass": "BreedLearnableMove"
        },
        {
          "move": "confide",
          "klass": "TechLearnableMove"
        },
        {
          "move": "high_horsepower",
          "klass": "BreedLearnableMove"
        },
        {
          "move": "rock_smash",
          "klass": "TechLearnableMove"
        },
        {
          "move": "strength",
          "klass": "TechLearnableMove"
        }
      ],
      "formTextId": {
        "name": 302,
        "description": 0
      }
    }
  ]
}