{
  "klass": "Specie",
  "id": 758,
  "dbSymbol": "salazzle",
  "forms": [
    {
      "form": 0,
      "height": 1.2,
      "weight": 22.2,
      "type1": "poison",
      "type2": "fire",
      "baseHp": 68,
      "baseAtk": 64,
      "baseDfe": 60,
      "baseSpd": 117,
      "baseAts": 111,
      "baseDfs": 60,
      "evHp": 0,
      "evAtk": 0,
      "evDfe": 0,
      "evSpd": 2,
      "evAts": 0,
      "evDfs": 0,
      "evolutions": [],
      "experienceType": 1,
      "baseExperience": 168,
      "baseLoyalty": 70,
      "catchRate": 45,
      "femaleRate": 100,
      "breedGroups": [
        14,
        1
      ],
      "hatchSteps": 5120,
      "babyDbSymbol": "salandit",
      "babyForm": 0,
      "itemHeld": [
        {
          "dbSymbol": "none",
          "chance": 0
        },
        {
          "dbSymbol": "none",
          "chance": 0
        }
      ],
      "abilities": [
        "corrosion",
        "corrosion",
        "oblivious"
      ],
      "frontOffsetY": 0,
      "resources": {
        "icon": "0758",
        "iconF": "0758",
        "iconShiny": "0758s",
        "iconShinyF": "0758s",
        "front": "0758",
        "frontF": "0758",
        "frontShiny": "0758s",
        "frontShinyF": "0758s",
        "back": "0758",
        "backF": "0758",
        "backShiny": "0758s",
        "backShinyF": "0758s",
        "footprint": "0758",
        "character": "0758",
        "characterF": "0758",
        "characterShiny": "0758s",
        "characterShinyF": "0758s",
        "cry": "0758.ogg",
        "hasFemale": true,
        "egg": "egg",
        "iconEgg": "egg"
      },
      "moveSet": [
        {
          "move": "pound",
          "klass": "LevelLearnableMove",
          "level": 1
        },
        {
          "move": "disable",
          "klass": "LevelLearnableMove",
          "level": 1
        },
        {
          "move": "ember",
          "klass": "LevelLearnableMove",
          "level": 1
        },
        {
          "move": "poison_gas",
          "klass": "LevelLearnableMove",
          "level": 1
        },
        {
          "move": "swagger",
          "klass": "LevelLearnableMove",
          "level": 1
        },
        {
          "move": "encore",
          "klass": "LevelLearnableMove",
          "level": 1
        },
        {
          "move": "sweet_scent",
          "klass": "LevelLearnableMove",
          "level": 1
        },
        {
          "move": "torment",
          "klass": "LevelLearnableMove",
          "level": 1
        },
        {
          "move": "captivate",
          "klass": "LevelLearnableMove",
          "level": 1
        },
        {
          "move": "ember",
          "klass": "LevelLearnableMove",
          "level": 5
        },
        {
          "move": "sweet_scent",
          "klass": "LevelLearnableMove",
          "level": 8
        },
        {
          "move": "dragon_rage",
          "klass": "LevelLearnableMove",
          "level": 13
        },
        {
          "move": "smog",
          "klass": "LevelLearnableMove",
          "level": 16
        },
        {
          "move": "double_slap",
          "klass": "LevelLearnableMove",
          "level": 21
        },
        {
          "move": "flame_burst",
          "klass": "LevelLearnableMove",
          "level": 24
        },
        {
          "move": "toxic",
          "klass": "LevelLearnableMove",
          "level": 29
        },
        {
          "move": "nasty_plot",
          "klass": "LevelLearnableMove",
          "level": 32
        },
        {
          "move": "venoshock",
          "klass": "LevelLearnableMove",
          "level": 39
        },
        {
          "move": "flamethrower",
          "klass": "LevelLearnableMove",
          "level": 44
        },
        {
          "move": "venom_drench",
          "klass": "LevelLearnableMove",
          "level": 51
        },
        {
          "move": "dragon_pulse",
          "klass": "LevelLearnableMove",
          "level": 56
        },
        {
          "move": "flamethrower",
          "klass": "TechLearnableMove"
        },
        {
          "move": "toxic",
          "klass": "TechLearnableMove"
        },
        {
          "move": "double_team",
          "klass": "TechLearnableMove"
        },
        {
          "move": "fire_blast",
          "klass": "TechLearnableMove"
        },
        {
          "move": "leech_life",
          "klass": "TechLearnableMove"
        },
        {
          "move": "rest",
          "klass": "TechLearnableMove"
        },
        {
          "move": "substitute",
          "klass": "TechLearnableMove"
        },
        {
          "move": "thief",
          "klass": "TechLearnableMove"
        },
        {
          "move": "snore",
          "klass": "TutorLearnableMove"
        },
        {
          "move": "protect",
          "klass": "TechLearnableMove"
        },
        {
          "move": "sludge_bomb",
          "klass": "TechLearnableMove"
        },
        {
          "move": "swagger",
          "klass": "TechLearnableMove"
        },
        {
          "move": "attract",
          "klass": "TechLearnableMove"
        },
        {
          "move": "sleep_talk",
          "klass": "TechLearnableMove"
        },
        {
          "move": "return",
          "klass": "TechLearnableMove"
        },
        {
          "move": "frustration",
          "klass": "TechLearnableMove"
        },
        {
          "move": "iron_tail",
          "klass": "TutorLearnableMove"
        },
        {
          "move": "hidden_power",
          "klass": "TechLearnableMove"
        },
        {
          "move": "heat_wave",
          "klass": "TutorLearnableMove"
        },
        {
          "move": "torment",
          "klass": "TechLearnableMove"
        },
        {
          "move": "will_o_wisp",
          "klass": "TechLearnableMove"
        },
        {
          "move": "facade",
          "klass": "TechLearnableMove"
        },
        {
          "move": "taunt",
          "klass": "TechLearnableMove"
        },
        {
          "move": "helping_hand",
          "klass": "TutorLearnableMove"
        },
        {
          "move": "knock_off",
          "klass": "TutorLearnableMove"
        },
        {
          "move": "snatch",
          "klass": "TutorLearnableMove"
        },
        {
          "move": "overheat",
          "klass": "TechLearnableMove"
        },
        {
          "move": "dragon_claw",
          "klass": "TechLearnableMove"
        },
        {
          "move": "covet",
          "klass": "TutorLearnableMove"
        },
        {
          "move": "payback",
          "klass": "TechLearnableMove"
        },
        {
          "move": "fling",
          "klass": "TechLearnableMove"
        },
        {
          "move": "poison_jab",
          "klass": "TechLearnableMove"
        },
        {
          "move": "dragon_pulse",
          "klass": "TutorLearnableMove"
        },
        {
          "move": "shadow_claw",
          "klass": "TechLearnableMove"
        },
        {
          "move": "gunk_shot",
          "klass": "TutorLearnableMove"
        },
        {
          "move": "captivate",
          "klass": "EvolutionLearnableMove"
        },
        {
          "move": "venoshock",
          "klass": "TechLearnableMove"
        },
        {
          "move": "sludge_wave",
          "klass": "TechLearnableMove"
        },
        {
          "move": "flame_charge",
          "klass": "TechLearnableMove"
        },
        {
          "move": "foul_play",
          "klass": "TutorLearnableMove"
        },
        {
          "move": "round",
          "klass": "TechLearnableMove"
        },
        {
          "move": "acrobatics",
          "klass": "TechLearnableMove"
        },
        {
          "move": "dragon_tail",
          "klass": "TechLearnableMove"
        },
        {
          "move": "confide",
          "klass": "TechLearnableMove"
        },
        {
          "move": "laser_focus",
          "klass": "TutorLearnableMove"
        }
      ],
      "formTextId": {
        "name": 975,
        "description": 0
      }
    }
  ]
}