{
  "klass": "Specie",
  "id": 220,
  "dbSymbol": "swinub",
  "forms": [
    {
      "form": 0,
      "height": 0.4,
      "weight": 6.5,
      "type1": "ice",
      "type2": "ground",
      "baseHp": 50,
      "baseAtk": 50,
      "baseDfe": 40,
      "baseSpd": 50,
      "baseAts": 30,
      "baseDfs": 30,
      "evHp": 0,
      "evAtk": 1,
      "evDfe": 0,
      "evSpd": 0,
      "evAts": 0,
      "evDfs": 0,
      "evolutions": [
        {
          "dbSymbol": "piloswine",
          "form": 0,
          "conditions": [
            {
              "type": "minLevel",
              "value": 33
            }
          ]
        }
      ],
      "experienceType": 2,
      "baseExperience": 50,
      "baseLoyalty": 70,
      "catchRate": 225,
      "femaleRate": 50,
      "breedGroups": [
        5,
        5
      ],
      "hatchSteps": 5120,
      "babyDbSymbol": "swinub",
      "babyForm": 0,
      "itemHeld": [
        {
          "dbSymbol": "none",
          "chance": 0
        },
        {
          "dbSymbol": "none",
          "chance": 0
        }
      ],
      "abilities": [
        "oblivious",
        "snow_cloak",
        "thick_fat"
      ],
      "frontOffsetY": 0,
      "moveSet": [
        {
          "klass": "LevelLearnableMove",
          "move": "tackle",
          "level": 1
        },
        {
          "klass": "LevelLearnableMove",
          "move": "odor_sleuth",
          "level": 1
        },
        {
          "klass": "LevelLearnableMove",
          "move": "mud_sport",
          "level": 5
        },
        {
          "klass": "LevelLearnableMove",
          "move": "powder_snow",
          "level": 8
        },
        {
          "klass": "LevelLearnableMove",
          "move": "mud_slap",
          "level": 11
        },
        {
          "klass": "LevelLearnableMove",
          "move": "endure",
          "level": 14
        },
        {
          "klass": "LevelLearnableMove",
          "move": "mud_bomb",
          "level": 18
        },
        {
          "klass": "LevelLearnableMove",
          "move": "icy_wind",
          "level": 21
        },
        {
          "klass": "LevelLearnableMove",
          "move": "ice_shard",
          "level": 24
        },
        {
          "klass": "LevelLearnableMove",
          "move": "take_down",
          "level": 28
        },
        {
          "klass": "LevelLearnableMove",
          "move": "mist",
          "level": 35
        },
        {
          "klass": "LevelLearnableMove",
          "move": "earthquake",
          "level": 37
        },
        {
          "klass": "LevelLearnableMove",
          "move": "flail",
          "level": 40
        },
        {
          "klass": "LevelLearnableMove",
          "move": "blizzard",
          "level": 44
        },
        {
          "klass": "LevelLearnableMove",
          "move": "amnesia",
          "level": 48
        },
        {
          "klass": "TutorLearnableMove",
          "move": "endeavor"
        },
        {
          "klass": "TutorLearnableMove",
          "move": "stealth_rock"
        },
        {
          "klass": "TutorLearnableMove",
          "move": "snore"
        },
        {
          "klass": "TutorLearnableMove",
          "move": "earth_power"
        },
        {
          "klass": "TutorLearnableMove",
          "move": "superpower"
        },
        {
          "klass": "TutorLearnableMove",
          "move": "icy_wind"
        },
        {
          "klass": "TechLearnableMove",
          "move": "roar"
        },
        {
          "klass": "TechLearnableMove",
          "move": "toxic"
        },
        {
          "klass": "TechLearnableMove",
          "move": "hail"
        },
        {
          "klass": "TechLearnableMove",
          "move": "hidden_power"
        },
        {
          "klass": "TechLearnableMove",
          "move": "ice_beam"
        },
        {
          "klass": "TechLearnableMove",
          "move": "blizzard"
        },
        {
          "klass": "TechLearnableMove",
          "move": "light_screen"
        },
        {
          "klass": "TechLearnableMove",
          "move": "protect"
        },
        {
          "klass": "TechLearnableMove",
          "move": "rain_dance"
        },
        {
          "klass": "TechLearnableMove",
          "move": "frustration"
        },
        {
          "klass": "TechLearnableMove",
          "move": "earthquake"
        },
        {
          "klass": "TechLearnableMove",
          "move": "return"
        },
        {
          "klass": "TechLearnableMove",
          "move": "double_team"
        },
        {
          "klass": "TechLearnableMove",
          "move": "reflect"
        },
        {
          "klass": "TechLearnableMove",
          "move": "sandstorm"
        },
        {
          "klass": "TechLearnableMove",
          "move": "rock_tomb"
        },
        {
          "klass": "TechLearnableMove",
          "move": "facade"
        },
        {
          "klass": "TechLearnableMove",
          "move": "rest"
        },
        {
          "klass": "TechLearnableMove",
          "move": "attract"
        },
        {
          "klass": "TechLearnableMove",
          "move": "round"
        },
        {
          "klass": "TechLearnableMove",
          "move": "bulldoze"
        },
        {
          "klass": "TechLearnableMove",
          "move": "rock_slide"
        },
        {
          "klass": "TechLearnableMove",
          "move": "swagger"
        },
        {
          "klass": "TechLearnableMove",
          "move": "sleep_talk"
        },
        {
          "klass": "TechLearnableMove",
          "move": "substitute"
        },
        {
          "klass": "TechLearnableMove",
          "move": "confide"
        },
        {
          "klass": "TechLearnableMove",
          "move": "secret_power"
        },
        {
          "klass": "TechLearnableMove",
          "move": "strength"
        },
        {
          "klass": "TechLearnableMove",
          "move": "rock_smash"
        },
        {
          "klass": "BreedLearnableMove",
          "move": "ancient_power"
        },
        {
          "klass": "BreedLearnableMove",
          "move": "avalanche"
        },
        {
          "klass": "BreedLearnableMove",
          "move": "bite"
        },
        {
          "klass": "BreedLearnableMove",
          "move": "body_slam"
        },
        {
          "klass": "BreedLearnableMove",
          "move": "curse"
        },
        {
          "klass": "BreedLearnableMove",
          "move": "double_edge"
        },
        {
          "klass": "BreedLearnableMove",
          "move": "fissure"
        },
        {
          "klass": "BreedLearnableMove",
          "move": "freeze_dry"
        },
        {
          "klass": "BreedLearnableMove",
          "move": "icicle_crash"
        },
        {
          "klass": "BreedLearnableMove",
          "move": "icicle_spear"
        },
        {
          "klass": "BreedLearnableMove",
          "move": "mud_shot"
        },
        {
          "klass": "BreedLearnableMove",
          "move": "stealth_rock"
        },
        {
          "klass": "BreedLearnableMove",
          "move": "take_down"
        }
      ],
      "resources": {
        "icon": "220",
        "iconShiny": "",
        "front": "220",
        "frontShiny": "220",
        "back": "220",
        "backShiny": "220",
        "footprint": "220",
        "character": "220_0",
        "characterShiny": "220s_0",
        "cry": "220cry.ogg",
        "hasFemale": false
      }
    }
  ]
}