{
  "klass": "Specie",
  "id": 734,
  "dbSymbol": "yungoos",
  "forms": [
    {
      "form": 0,
      "height": 0.4,
      "weight": 6,
      "type1": "normal",
      "type2": "__undef__",
      "baseHp": 48,
      "baseAtk": 70,
      "baseDfe": 30,
      "baseSpd": 45,
      "baseAts": 30,
      "baseDfs": 30,
      "evHp": 0,
      "evAtk": 1,
      "evDfe": 0,
      "evSpd": 0,
      "evAts": 0,
      "evDfs": 0,
      "evolutions": [
        {
          "dbSymbol": "gumshoos",
          "form": 0,
          "conditions": [
            {
              "type": "minLevel",
              "value": 20
            }
          ]
        }
      ],
      "experienceType": 1,
      "baseExperience": 51,
      "baseLoyalty": 70,
      "catchRate": 255,
      "femaleRate": 50,
      "breedGroups": [
        5,
        5
      ],
      "hatchSteps": 3840,
      "babyDbSymbol": "yungoos",
      "babyForm": 0,
      "itemHeld": [
        {
          "dbSymbol": "pecha_berry",
          "chance": 5
        },
        {
          "dbSymbol": "none",
          "chance": 0
        }
      ],
      "abilities": [
        "stakeout",
        "strong_jaw",
        "adaptability"
      ],
      "frontOffsetY": 0,
      "moveSet": [
        {
          "klass": "LevelLearnableMove",
          "move": "tackle",
          "level": 1
        },
        {
          "klass": "LevelLearnableMove",
          "move": "leer",
          "level": 3
        },
        {
          "klass": "LevelLearnableMove",
          "move": "pursuit",
          "level": 7
        },
        {
          "klass": "LevelLearnableMove",
          "move": "sand_attack",
          "level": 10
        },
        {
          "klass": "LevelLearnableMove",
          "move": "odor_sleuth",
          "level": 13
        },
        {
          "klass": "LevelLearnableMove",
          "move": "bide",
          "level": 16
        },
        {
          "klass": "LevelLearnableMove",
          "move": "bite",
          "level": 19
        },
        {
          "klass": "LevelLearnableMove",
          "move": "mud_slap",
          "level": 22
        },
        {
          "klass": "LevelLearnableMove",
          "move": "super_fang",
          "level": 25
        },
        {
          "klass": "LevelLearnableMove",
          "move": "take_down",
          "level": 28
        },
        {
          "klass": "LevelLearnableMove",
          "move": "scary_face",
          "level": 31
        },
        {
          "klass": "LevelLearnableMove",
          "move": "crunch",
          "level": 34
        },
        {
          "klass": "LevelLearnableMove",
          "move": "hyper_fang",
          "level": 37
        },
        {
          "klass": "LevelLearnableMove",
          "move": "yawn",
          "level": 40
        },
        {
          "klass": "LevelLearnableMove",
          "move": "thrash",
          "level": 43
        },
        {
          "klass": "LevelLearnableMove",
          "move": "rest",
          "level": 46
        },
        {
          "klass": "TutorLearnableMove",
          "move": "super_fang"
        },
        {
          "klass": "TutorLearnableMove",
          "move": "last_resort"
        },
        {
          "klass": "TutorLearnableMove",
          "move": "endeavor"
        },
        {
          "klass": "TutorLearnableMove",
          "move": "shock_wave"
        },
        {
          "klass": "TutorLearnableMove",
          "move": "iron_tail"
        },
        {
          "klass": "TutorLearnableMove",
          "move": "snore"
        },
        {
          "klass": "TutorLearnableMove",
          "move": "uproar"
        },
        {
          "klass": "TutorLearnableMove",
          "move": "stomping_tantrum"
        },
        {
          "klass": "TechLearnableMove",
          "move": "work_up"
        },
        {
          "klass": "TechLearnableMove",
          "move": "toxic"
        },
        {
          "klass": "TechLearnableMove",
          "move": "hidden_power"
        },
        {
          "klass": "TechLearnableMove",
          "move": "taunt"
        },
        {
          "klass": "TechLearnableMove",
          "move": "protect"
        },
        {
          "klass": "TechLearnableMove",
          "move": "frustration"
        },
        {
          "klass": "TechLearnableMove",
          "move": "earthquake"
        },
        {
          "klass": "TechLearnableMove",
          "move": "return"
        },
        {
          "klass": "TechLearnableMove",
          "move": "double_team"
        },
        {
          "klass": "TechLearnableMove",
          "move": "sandstorm"
        },
        {
          "klass": "TechLearnableMove",
          "move": "rock_tomb"
        },
        {
          "klass": "TechLearnableMove",
          "move": "torment"
        },
        {
          "klass": "TechLearnableMove",
          "move": "facade"
        },
        {
          "klass": "TechLearnableMove",
          "move": "rest"
        },
        {
          "klass": "TechLearnableMove",
          "move": "attract"
        },
        {
          "klass": "TechLearnableMove",
          "move": "thief"
        },
        {
          "klass": "TechLearnableMove",
          "move": "round"
        },
        {
          "klass": "TechLearnableMove",
          "move": "echoed_voice"
        },
        {
          "klass": "TechLearnableMove",
          "move": "payback"
        },
        {
          "klass": "TechLearnableMove",
          "move": "swagger"
        },
        {
          "klass": "TechLearnableMove",
          "move": "sleep_talk"
        },
        {
          "klass": "TechLearnableMove",
          "move": "u_turn"
        },
        {
          "klass": "TechLearnableMove",
          "move": "substitute"
        },
        {
          "klass": "TechLearnableMove",
          "move": "confide"
        },
        {
          "klass": "TechLearnableMove",
          "move": "secret_power"
        },
        {
          "klass": "TechLearnableMove",
          "move": "cut"
        },
        {
          "klass": "TechLearnableMove",
          "move": "rock_smash"
        },
        {
          "klass": "BreedLearnableMove",
          "move": "fire_fang"
        },
        {
          "klass": "BreedLearnableMove",
          "move": "ice_fang"
        },
        {
          "klass": "BreedLearnableMove",
          "move": "last_resort"
        },
        {
          "klass": "BreedLearnableMove",
          "move": "revenge"
        },
        {
          "klass": "BreedLearnableMove",
          "move": "thunder_fang"
        }
      ],
      "resources": {
        "icon": "734",
        "iconShiny": "",
        "front": "734",
        "frontShiny": "734",
        "back": "734",
        "backShiny": "734",
        "footprint": "",
        "character": "734_0",
        "characterShiny": "734s_0",
        "cry": "734cry.ogg",
        "hasFemale": false
      }
    }
  ]
}